{ "storages":
  {
    "cache": { "name": "texpert-test-cache", "prefix": "cache" },
    "store": { "name": "texpert-test-store", "prefix": "store", "upload_options": { "acl": "private" } }
  },
  "path": "feed/3/logo/d46bd213658257d4913247d62d74760f.png",
  "callbackURL": "https://b329-109-185-141-9.ngrok.io/rapi/lambda",
  "target_storage": "store",
  "copy_original": true,
  "context": { "record": ["Feed", 3], "name": "logo", "shrine_class": "LambdaUploader"},
  "attachment": { "id": "doggy.png",
                  "storage": "cache",
                  "metadata": {
                    "size": 64684,
                    "filename": "doggy.png",
                    "key": "big_secret",
                    "mime_type": "image/png" }
  },
  "versions":
  [
    { "name": "size_40_40",
      "storage": "store",
      "width": 40,
      "height": 40,
      "background": "transparent",
      "format": "jpg" },
    { "name": "size_50_50",
      "storage": "store",
      "width": 50,
      "height": 50,
      "background": "transparent"}
  ]
}
